pygeoops/__init__.py
pygeoops/_centerline.py
pygeoops/_difference.py
pygeoops/_extend_line.py
pygeoops/_general.py
pygeoops/_grid.py
pygeoops/_paramvalidation.py
pygeoops/_simplify.py
pygeoops/_simplify_lang.py
pygeoops/_simplify_topo.py
pygeoops/_types.py
pygeoops/_view_angles.py
pygeoops/py.typed
pygeoops/version.txt
pygeoops-0.5.0.post1.dist-info/licenses/LICENSE.txt
pygeoops-0.5.0.post1.dist-info/METADATA
pygeoops-0.5.0.post1.dist-info/WHEEL
pygeoops-0.5.0.post1.dist-info/top_level.txt
pygeoops-0.5.0.post1.dist-info/RECORD
