Metadata-Version: 2.4
Name: pygeoops
Version: 0.5.0.post1
Summary: Library with some less common or extended spatial functions
Author-email: Pieter Roggemans <pieter.roggemans@gmail.com>
License: BSD-3-Clause
Project-URL: Homepage, https://github.com/pygeoops/pygeoops
Project-URL: Bug Tracker, https://github.com/pygeoops/pygeoops/issues
Keywords: GIS,cartography,pandas,shapely,geopandas
Classifier: Programming Language :: Python :: 3
Classifier: Operating System :: OS Independent
Requires-Python: >=3.10
License-File: LICENSE.txt
Requires-Dist: geopandas>=0.12.1
Requires-Dist: numpy
Requires-Dist: pyproj
Requires-Dist: shapely>1
Requires-Dist: topojson
Provides-Extra: full
Requires-Dist: simplification; extra == "full"
Dynamic: license-file
